memician/__init__.py
memician/__main__.py
memician/version.py
zf_memician-0.1.3.dist-info/LICENSE
zf_memician-0.1.3.dist-info/METADATA
zf_memician-0.1.3.dist-info/WHEEL
zf_memician-0.1.3.dist-info/entry_points.txt
zf_memician-0.1.3.dist-info/top_level.txt
zf_memician-0.1.3.dist-info/RECORD
