Metadata-Version: 2.1
Name: zf-memician
Version: 0.1.3
Summary: Memician is a state of the art Memelord
Author: Zeff Muks
Author-email: zeffmuks@gmail.com
License: PROPRIETARY
License-File: LICENSE
Requires-Dist: annotated-types ==0.7.0
Requires-Dist: anyio ==4.4.0
Requires-Dist: certifi ==2024.7.4
Requires-Dist: charset-normalizer ==3.3.2
Requires-Dist: distro ==1.9.0
Requires-Dist: h11 ==0.14.0
Requires-Dist: httpcore ==1.0.5
Requires-Dist: httpx ==0.27.0
Requires-Dist: idna ==3.7
Requires-Dist: jiter ==0.5.0
Requires-Dist: loguru ==0.7.2
Requires-Dist: openai ==1.40.3
Requires-Dist: pillow ==10.4.0
Requires-Dist: praw ==7.7.1
Requires-Dist: prawcore ==2.4.0
Requires-Dist: pydantic ==2.8.2
Requires-Dist: pydantic-core ==2.20.1
Requires-Dist: requests ==2.32.3
Requires-Dist: sniffio ==1.3.1
Requires-Dist: sqlite-vec ==0.1.1
Requires-Dist: tqdm ==4.66.5
Requires-Dist: typing-extensions ==4.12.2
Requires-Dist: update-checker ==0.18.0
Requires-Dist: urllib3 ==2.2.2
Requires-Dist: websocket-client ==1.8.0
